pylatesttrends/__init__.py
pylatesttrends/data.py
pylatesttrends/trends_scraper.py
pylatesttrends-0.1.7.dist-info/licenses/LICENSE
pylatesttrends-0.1.7.dist-info/METADATA
pylatesttrends-0.1.7.dist-info/WHEEL
pylatesttrends-0.1.7.dist-info/top_level.txt
pylatesttrends-0.1.7.dist-info/RECORD
