Metadata-Version: 2.4
Name: pylatesttrends
Version: 0.1.7
Summary: Get the latest trends from Google Trends
Author: Farasat Ali
Author-email: Farasat Ali <63093876+faraasat@users.noreply.github.com>
License: GPLv3
Project-URL: Homepage, https://github.com/faraasat/pylatesttrends
Classifier: Programming Language :: Python :: 3
Classifier: License :: OSI Approved :: GNU General Public License v3 (GPLv3)
Classifier: Operating System :: OS Independent
Requires-Python: >=3.9
License-File: LICENSE
Requires-Dist: selenium
Requires-Dist: pandas
Requires-Dist: webdriver_manager
Dynamic: author
Dynamic: license-file
Dynamic: requires-python
